seq_dbutils/__init__.py
seq_dbutils/_version.txt
seq_dbutils/args.py
seq_dbutils/config.py
seq_dbutils/connection.py
seq_dbutils/dataframe.py
seq_dbutils/decrypt.py
seq_dbutils/encrypt.py
seq_dbutils/load.py
seq_dbutils/session.py
seq_dbutils/table.py
seq_dbutils/trigger.py
seq_dbutils/view.py
seq_dbutils-2.0.2.dist-info/LICENSE
seq_dbutils-2.0.2.dist-info/METADATA
seq_dbutils-2.0.2.dist-info/WHEEL
seq_dbutils-2.0.2.dist-info/top_level.txt
seq_dbutils-2.0.2.dist-info/RECORD
