Metadata-Version: 2.1
Name: seq_dbutils
Version: 2.0.2
Summary: A package of MySQL database utilities
Home-page: https://github.com/BDI-pathogens/seq_dbutils
Author: Laura Thomson
Author-email: laura.thomson@bdi.ox.ac.uk
License: MIT
Platform: any
Classifier: Programming Language :: Python
Classifier: Programming Language :: Python :: 3
Classifier: Programming Language :: Python :: 3.9
Classifier: Programming Language :: Python :: 3.10
Classifier: Programming Language :: Python :: 3.11
Classifier: Programming Language :: Python :: 3.12
Classifier: Intended Audience :: Developers
Classifier: License :: OSI Approved :: MIT License
Classifier: Topic :: Software Development :: Libraries :: Python Modules
Classifier: Operating System :: OS Independent
Requires-Python: <3.13,>=3.9
License-File: LICENSE
Requires-Dist: cryptography~=43.0.1
Requires-Dist: mysql-connector-python~=8.1.0
Requires-Dist: pandas~=2.1.1
Requires-Dist: SQLAlchemy~=2.0.22
